MANIFEST.in
__info__.py
setup.py
./appomatic_appadmin.egg-info/SOURCES.txt
./appomatic_appadmin.egg-info/dependency_links.txt
./appomatic_appadmin.egg-info/requires.txt
./appomatic_appadmin.egg-info/top_level.txt
./appomatic_appadmin/static/appomatic_appadmin/css/progress.css
./appomatic_appadmin/static/appomatic_appadmin/js/jquery.js
./appomatic_appadmin/static/appomatic_appadmin/js/progress.js
./appomatic_appadmin/templates/appomatic_appadmin/add.html
./appomatic_appadmin/templates/appomatic_appadmin/details.html
./appomatic_appadmin/templates/appomatic_appadmin/index.html
./appomatic_appadmin/templates/appomatic_appadmin/progress_display.html
appomatic_appadmin/__app__.py
appomatic_appadmin/__init__.py
appomatic_appadmin/__urls__.py
appomatic_appadmin/models.py
appomatic_appadmin/views.py
appomatic_appadmin.egg-info/PKG-INFO
appomatic_appadmin.egg-info/SOURCES.txt
appomatic_appadmin.egg-info/dependency_links.txt
appomatic_appadmin.egg-info/requires.txt
appomatic_appadmin.egg-info/top_level.txt
appomatic_appadmin/static/__init__.py
appomatic_appadmin/static/appomatic_appadmin/__init__.py
appomatic_appadmin/static/appomatic_appadmin/css/__init__.py
appomatic_appadmin/static/appomatic_appadmin/js/__init__.py
appomatic_appadmin/templates/__init__.py
appomatic_appadmin/templates/appomatic_appadmin/__init__.py
appomatic_appadmin/utils/__init__.py
appomatic_appadmin/utils/action.py
appomatic_appadmin/utils/app.py
appomatic_appadmin/utils/reload.py