Metadata-Version: 1.0
Name: appomatic-appadmin
Version: 0.0.32
Summary: Django admin page to administer appomatic apps
Home-page: http://github.com/redhog/appomatic
Author: RedHog (Egil Moeller)
Author-email: egil.moller@freecode.no
License: GPL
Keywords: appomatic django-admin
Platform: UNKNOWN
